Metadata-Version: 2.1
Name: gado
Version: 0.0.5
Summary: generate poetry with gcc diagnostics
Home-page: https://github.com/diksown/gado
Author: Dikson Santos
Author-email: diksonfer@gmail.com
License: MIT
Keywords: gcc poetry nlp
Platform: UNKNOWN
Classifier: Programming Language :: Python :: 3
Classifier: License :: OSI Approved :: MIT License
Classifier: Operating System :: Unix
Classifier: Environment :: Console
License-File: LICENSE
